ratteil/__init__.py
ratteil/__main__.py
ratteil/base.py
ratteil/base_test.py
ratteil/client_secrets.json
ratteil/create_fb.py
ratteil/create_stream.py
ratteil/dl.py
ratteil/install.sh
ratteil/reciters.py
ratteil/requirements.txt
ratteil/surahs.py
ratteil/docs/README.md
ratteil/fixer/conclusion.mp4
ratteil/fixer/introduction.mp4
ratteil/imgs/0.jpg
ratteil/imgs/1.jpg
ratteil/imgs/2.jpg
ratteil/imgs/3.jpg
ratteil/imgs/4.jpg
ratteil/imgs/5.jpg
ratteil/imgs/6.jpg
ratteil-2024.7.3.1.dist-info/LICENSE
ratteil-2024.7.3.1.dist-info/METADATA
ratteil-2024.7.3.1.dist-info/NOTICE
ratteil-2024.7.3.1.dist-info/WHEEL
ratteil-2024.7.3.1.dist-info/entry_points.txt
ratteil-2024.7.3.1.dist-info/top_level.txt
ratteil-2024.7.3.1.dist-info/RECORD
