Metadata-Version: 2.1
Name: ratteil
Version: 2024.7.3.1
Summary: Livestreaming the Holly Quran to youtube
Author-email: Ali Elfatih <alielfatih@hotmail.com>
License: GNU GENERAL PUBLIC LICENSE
Keywords: Quran,the Holly Quran,Youtube,streaming,Live stream
Classifier: Development Status :: 4 - Beta
Classifier: Environment :: Console
Classifier: Intended Audience :: End Users/Desktop
Classifier: Operating System :: OS Independent
Classifier: Programming Language :: Python :: 3
Classifier: Topic :: Internet
Classifier: Topic :: Multimedia :: Sound/Audio :: Capture/Recording
Classifier: Topic :: Religion
Requires-Python: >=3.7
License-File: LICENSE
License-File: NOTICE
Requires-Dist: google-api-python-client ==1.7.2
Requires-Dist: google-auth ==1.8.0
Requires-Dist: google-auth-httplib2 ==0.0.3
Requires-Dist: google-auth-oauthlib ==0.4.1
Requires-Dist: oauth2client
